{
  "compilerOptions": {
    "lib": [
      "dom",
      "es2015",
      "es2016",
      "es2017",
      "es2018",
      "es2019",
      "es2020",
      "es2021",
      "esnext"
    ],
    "strict": true,
    "noImplicitReturns": true
  },
  "importMap": "./import_map.json",
  "tasks": {
    "play": "deno run --unstable --allow-net --allow-read --allow-env --unsafely-ignore-certificate-errors=localhost test.ts",
    "edgeql-js": "deno run -A --unstable --unsafely-ignore-certificate-errors=localhost ../../deno/generate.ts edgeql-js --output-dir edgeql-js --target deno",
    "queries": "deno run -A --unstable --unsafely-ignore-certificate-errors=localhost ../../deno/generate.ts queries --target deno --file queries",
    "interfaces": "deno run -A --unstable --unsafely-ignore-certificate-errors=localhost ../../deno/generate.ts interfaces --file ifaces"
  }
}
